nucleaizer_backend/__init__.py
nucleaizer_backend/common.py
nucleaizer_backend/load_python_module.py
nucleaizer_backend/matlab_func_wrapper.py
nucleaizer_backend/matlab_interfaces.py
nucleaizer_backend/model_accessors.py
nucleaizer_backend/mrcnn_config.py
nucleaizer_backend/nucleaizer_backend.py
nucleaizer_backend/remote.py
nucleaizer_backend/training.py
nucleaizer_backend/training_cli.py
nucleaizer_backend/CycleGAN/generate_images.py
nucleaizer_backend/CycleGAN/learn_styles.py
nucleaizer_backend/CycleGAN/process_results.py
nucleaizer_backend/CycleGAN/test.py
nucleaizer_backend/CycleGAN/test_cus.py
nucleaizer_backend/CycleGAN/test_cus_orig.py
nucleaizer_backend/CycleGAN/train.py
nucleaizer_backend/Mask_RCNN_tf2/setup.py
nucleaizer_backend/Mask_RCNN_tf2/mrcnn/__init__.py
nucleaizer_backend/Mask_RCNN_tf2/mrcnn/config.py
nucleaizer_backend/Mask_RCNN_tf2/mrcnn/model.py
nucleaizer_backend/Mask_RCNN_tf2/mrcnn/parallel_model.py
nucleaizer_backend/Mask_RCNN_tf2/mrcnn/utils.py
nucleaizer_backend/Mask_RCNN_tf2/mrcnn/visualize.py
nucleaizer_backend/_tests/__init__.py
nucleaizer_backend/_tests/test_training.py
nucleaizer_backend/mrcnn_interface/image_augmentation.py
nucleaizer_backend/mrcnn_interface/kutils.py
nucleaizer_backend/mrcnn_interface/mask_rcnn_additional.py
nucleaizer_backend/mrcnn_interface/nuclei_config.py
nucleaizer_backend/mrcnn_interface/nuclei_dataset.py
nucleaizer_backend/mrcnn_interface/predict.py
nucleaizer_backend/mrcnn_interface/train.py
nucleaizer_backend/mrcnn_interface/_tests/test_predict.py
nucleaizer_backend/pix2pix_interface/style_transfer.py
nucleaizer_backend-0.2.6.dist-info/AUTHORS.rst
nucleaizer_backend-0.2.6.dist-info/LICENSE
nucleaizer_backend-0.2.6.dist-info/METADATA
nucleaizer_backend-0.2.6.dist-info/WHEEL
nucleaizer_backend-0.2.6.dist-info/entry_points.txt
nucleaizer_backend-0.2.6.dist-info/top_level.txt
nucleaizer_backend-0.2.6.dist-info/RECORD
