Metadata-Version: 2.1
Name: nucleaizer-backend
Version: 0.2.6
Summary: The backend for the nucleAIzer nuclei segmentation method.
Home-page: https://github.com/etasnadi/nucleaizer_backend
Author: Ervin Tasnadi
Author-email: tasnadi.ervin@brc.hu
License: GPL-3.0
Project-URL: Bug Tracker, https://github.com/etasnadi/nucleaizer_backend/issues
Project-URL: Documentation, https://napari-nucleaizer-docs.readthedocs.io/en/latest/index.html
Project-URL: Source Code, https://github.com/etasnadi/nucleaizer_backend
Project-URL: User Support, https://github.com/etasnadi/nucleaizer_backend/issues
Classifier: Development Status :: 3 - Alpha
Classifier: Intended Audience :: Developers
Classifier: Framework :: napari
Classifier: Topic :: Software Development :: Testing
Classifier: Programming Language :: Python
Classifier: Programming Language :: Python :: 3
Classifier: Programming Language :: Python :: 3.8
Classifier: Programming Language :: Python :: 3.9
Classifier: Programming Language :: Python :: 3.10
Classifier: Operating System :: OS Independent
Classifier: License :: OSI Approved :: BSD License
Requires-Python: >=3.8
License-File: LICENSE
License-File: AUTHORS.rst
Requires-Dist: numpy >=1.18.5
Requires-Dist: scipy >=1.4.1
Requires-Dist: Cython
Requires-Dist: tqdm
Requires-Dist: albumentations
Requires-Dist: opencv-python >=4.5.1
Requires-Dist: tensorflow >=2.3
Requires-Dist: imageio >=2.9.0
Requires-Dist: imagecodecs
Requires-Dist: matplotlib
Requires-Dist: scikit-image >=0.18.1
Requires-Dist: ipython
Requires-Dist: torch >=1.8.1
Requires-Dist: torchvision >=0.9.1
Requires-Dist: dominate
